{
    "game": "samus_returns",
    "elements": [
        {
            "row": 1,
            "column": 0,
            "resources": [
                "Morph Ball"
            ],
            "kind": "image"
        },
        {
            "row": 1,
            "column": 1,
            "resources": [
                "Spider Ball"
            ],
            "kind": "image"
        },
        {
            "row": 1,
            "column": 2,
            "resources": [
                "Spring Ball"
            ],
            "kind": "image"
        },
        {
            "row": 1,
            "column": 3,
            "resources": [
                "Bomb"
            ],
            "kind": "image"
        },
        {
            "row": 1,
            "column": 4,
            "resources": [
                "Power Bomb Launcher"
            ],
            "kind": "image"
        },
        {
            "row": 2,
            "column": 0,
            "resources": [
                "Wave Beam"
            ],
            "kind": "image"
        },
        {
            "row": 2,
            "column": 1,
            "resources": [
                "Spazer Beam"
            ],
            "kind": "image"
        },
        {
            "row": 2,
            "column": 2,
            "resources": [
                "Plasma Beam"
            ],
            "kind": "image"
        },
        {
            "row": 2,
            "column": 3,
            "resources": [
                "Charge Beam"
            ],
            "kind": "image"
        },
        {
            "row": 2,
            "column": 4,
            "resources": [
                "Ice Beam"
            ],
            "kind": "image"
        },
        {
            "row": 3,
            "column": 0,
            "resources": [
                "Missile Launcher"
            ],
            "kind": "image"
        },
        {
            "row": 3,
            "column": 1,
            "resources": [
                "Super Missile Launcher"
            ],
            "kind": "image"
        },
        {
            "row": 3,
            "column": 3,
            "resources": [
                "Varia Suit"
            ],
            "kind": "image"
        },
        {
            "row": 3,
            "column": 4,
            "resources": [
                "Gravity Suit"
            ],
            "kind": "image"
        },
        {
            "row": 4,
            "column": 0,
            "resources": [
                "High Jump Boots"
            ],
            "kind": "image"
        },
        {
            "row": 4,
            "column": 1,
            "resources": [
                "Space Jump"
            ],
            "kind": "image"
        },
        {
            "row": 4,
            "column": 3,
            "resources": [
                "Grapple Beam"
            ],
            "kind": "image"
        },
        {
            "row": 4,
            "column": 4,
            "resources": [
                "Screw Attack"
            ],
            "kind": "image"
        },
        {
            "row": 5,
            "column": 0,
            "col_span": 2,
            "resources": [
                "Scan Pulse"
            ],
            "kind": "image"
        },
        {
            "row": 5,
            "column": 1,
            "col_span": 2,
            "resources": [
                "Lightning Armor"
            ],
            "kind": "image"
        },
        {
            "row": 5,
            "column": 2,
            "col_span": 2,
            "resources": [
                "Beam Burst"
            ],
            "kind": "image"
        },
        {
            "row": 5,
            "column": 3,
            "col_span": 2,
            "resources": [
                "Phase Drift"
            ],
            "kind": "image"
        },
        {
            "row": 6,
            "column": 0,
            "resources": [
                "Energy Reserve Tank"
            ],
            "kind": "image"
        },
        {
            "row": 6,
            "column": 1,
            "resources": [
                "Aeion Reserve Tank"
            ],
            "kind": "image"
        },
        {
            "row": 6,
            "column": 2,
            "resources": [
                "Missile Reserve Tank"
            ],
            "kind": "image"
        },
        {
            "row": 6,
            "column": 3,
            "resources": [
                "Baby Metroid"
            ],
            "kind": "image"
        },
        {
            "row": 6,
            "column": 4,
            "resources": [],
            "kind": "image"
        },
        {
            "row": 7,
            "column": 3,
            "col_span": 3,
            "resources": [
                "Collected Metroid DNA"
            ],
            "kind": "label"
        },
        {
            "row": 7,
            "column": 4,
            "resources": [
                "Required Metroid DNA"
            ],
            "kind": "label"
        }
    ],
    "extra": {}
}