{
    "name": "Main",
    "extra": {},
    "areas": {
        "First Area": {
            "default_node": null,
            "hint_features": [],
            "extra": {},
            "nodes": {
                "Spawn Point": {
                    "node_type": "generic",
                    "heal": false,
                    "coordinates": null,
                    "description": "",
                    "layers": [
                        "default"
                    ],
                    "extra": {},
                    "valid_starting_location": true,
                    "connections": {
                        "Pickup (One)": {
                            "type": "and",
                            "data": {
                                "comment": null,
                                "items": []
                            }
                        },
                        "Pickup (Two)": {
                            "type": "and",
                            "data": {
                                "comment": null,
                                "items": []
                            }
                        }
                    }
                },
                "Pickup (One)": {
                    "node_type": "pickup",
                    "heal": false,
                    "coordinates": null,
                    "description": "",
                    "layers": [
                        "default"
                    ],
                    "extra": {},
                    "valid_starting_location": true,
                    "pickup_index": 0,
                    "location_category": "major",
                    "hint_features": [],
                    "connections": {
                        "Spawn Point": {
                            "type": "and",
                            "data": {
                                "comment": null,
                                "items": []
                            }
                        },
                        "Pickup (Two)": {
                            "type": "and",
                            "data": {
                                "comment": null,
                                "items": []
                            }
                        }
                    }
                },
                "Pickup (Two)": {
                    "node_type": "pickup",
                    "heal": false,
                    "coordinates": null,
                    "description": "",
                    "layers": [
                        "default"
                    ],
                    "extra": {},
                    "valid_starting_location": true,
                    "pickup_index": 1,
                    "location_category": "minor",
                    "hint_features": [],
                    "connections": {
                        "Spawn Point": {
                            "type": "and",
                            "data": {
                                "comment": null,
                                "items": []
                            }
                        },
                        "Pickup (One)": {
                            "type": "and",
                            "data": {
                                "comment": null,
                                "items": []
                            }
                        }
                    }
                }
            }
        }
    }
}